Candataloader/Survival Analysis Dataset for automobile IDS.csv
Candataloader/SynCAN.csv
Candataloader/__init__.py
Candataloader/download.py
Candataloader/datasets/Survival Analysis Dataset for automobile IDS.csv
Candataloader/datasets/SynCAN.csv
download_dataset/__init__.py
download_dataset/download.py
Candataloader-1.1.7.dist-info/METADATA
Candataloader-1.1.7.dist-info/WHEEL
Candataloader-1.1.7.dist-info/top_level.txt
Candataloader-1.1.7.dist-info/RECORD
