Metadata-Version: 2.1
Name: Candataloader
Version: 1.1.7
Summary: A library for downloading datasets
Home-page: UNKNOWN
Author: PhongPhat
Author-email: 19522010@gm.uit.edu.vn
License: MIT
Platform: UNKNOWN
